{
  "session_id": "free_space_continous_50",
  "episode_id": "ep_free_space_continuous_006",
  "timestamp": "20260712_140726",
  "bag": "ep_free_space_continuous_006_20260712_140726.bag",
  "duration_sec": 50,
  "excitation": "free_space",
  "control_mode": "PWM",
  "warmup": "warm",
  "driver_version": "unknown",
  "operator_notes": "",
  "ros_master_uri": "http://localhost:11311",
  "recorded_topics": [
    "/joint_states",
    "/shadow_touchlab_translator/calibrated",
    "/sh_rh_ffj0_position_controller/state",
    "/sh_rh_ffj3_position_controller/state",
    "/sh_rh_ffj4_position_controller/state",
    "/sh_rh_mfj0_position_controller/state",
    "/sh_rh_mfj3_position_controller/state",
    "/sh_rh_mfj4_position_controller/state",
    "/sh_rh_rfj0_position_controller/state",
    "/sh_rh_rfj3_position_controller/state",
    "/sh_rh_rfj4_position_controller/state",
    "/sh_rh_thj1_position_controller/state",
    "/sh_rh_thj2_position_controller/state",
    "/sh_rh_thj4_position_controller/state",
    "/sh_rh_thj5_position_controller/state",
    "/diagnostics"
  ],
  "regime": "free_space_continuous",
  "families": [
    "ou_walk",
    "multisine",
    "chirp"
  ],
  "rng_seed": 1934531657,
  "duration_s": 38.61272792019073,
  "family_seeds": {
    "ou_walk": 1475768801,
    "multisine": 814209768,
    "chirp": 1280507473
  },
  "command_space": "actuator_order",
  "publish_rate_hz": 60.0,
  "max_delta_rad": 0.05741327291735436,
  "loop_jitter_ms": {
    "mean": 0.1178013774572849,
    "p50": 0.08726119995117188,
    "p95": 0.19688606262207015,
    "max": 8.067846298217773
  },
  "loop_overruns": 2437,
  "per_channel_delta_max": {
    "rh_FFJ0": 0.04153804132424144,
    "rh_FFJ3": 0.036087137214180776,
    "rh_FFJ4": 0.028398061863658564,
    "rh_MFJ0": 0.04038651598545595,
    "rh_MFJ3": 0.03322072658173192,
    "rh_MFJ4": 0.018505223224207785,
    "rh_RFJ0": 0.040872202902636934,
    "rh_RFJ3": 0.029630807817190075,
    "rh_RFJ4": 0.02452401395720399,
    "rh_THJ1": 0.02766339513383731,
    "rh_THJ2": 0.02895969270066933,
    "rh_THJ4": 0.02913651731735234,
    "rh_THJ5": 0.03830164367738346
  },
  "per_channel_delta_p95": {
    "rh_FFJ0": 0.023823892415912096,
    "rh_FFJ3": 0.02234283811788848,
    "rh_FFJ4": 0.017205853144550615,
    "rh_MFJ0": 0.024497819468473014,
    "rh_MFJ3": 0.020234070643177032,
    "rh_MFJ4": 0.012217207381794465,
    "rh_RFJ0": 0.02359029498456683,
    "rh_RFJ3": 0.01886491192410783,
    "rh_RFJ4": 0.01682980798601859,
    "rh_THJ1": 0.018712646401891825,
    "rh_THJ2": 0.018904215262628025,
    "rh_THJ4": 0.0175190145632661,
    "rh_THJ5": 0.021226168606662252
  },
  "step_events": [],
  "native_rates_hz": {
    "joint_states": 125,
    "controller_state": 87,
    "diagnostics": 2
  },
  "home_pose_actuator": {
    "rh_FFJ0": 1.74,
    "rh_FFJ3": 0.65,
    "rh_FFJ4": -0.33513600000000004,
    "rh_MFJ0": 1.74,
    "rh_MFJ3": 0.65,
    "rh_MFJ4": 0.0,
    "rh_RFJ0": 1.74,
    "rh_RFJ3": 0.65,
    "rh_RFJ4": -0.33513600000000004,
    "rh_THJ1": 0.0,
    "rh_THJ2": 0.35,
    "rh_THJ4": 0.5,
    "rh_THJ5": 0.4
  },
  "home_settle_s": 4.0,
  "pre_episode_setpoint_gap": {
    "process_value": {
      "rh_FFJ0": 1.7345188096277933,
      "rh_FFJ3": 0.6487644419376398,
      "rh_FFJ4": -0.3334291687844255,
      "rh_MFJ0": 1.7365035416385275,
      "rh_MFJ3": 0.6486749627205808,
      "rh_MFJ4": -0.0036616148041375856,
      "rh_RFJ0": 1.7395741101184963,
      "rh_RFJ3": 0.6500571061721582,
      "rh_RFJ4": -0.3363401384993168,
      "rh_THJ1": 0.007689686444523178,
      "rh_THJ2": 0.3441945938628641,
      "rh_THJ4": 0.5028595763894257,
      "rh_THJ5": 0.3971946920940424
    },
    "set_point": {
      "rh_FFJ0": 1.74,
      "rh_FFJ3": 0.65,
      "rh_FFJ4": -0.33513600000000004,
      "rh_MFJ0": 1.74,
      "rh_MFJ3": 0.65,
      "rh_MFJ4": 0.0,
      "rh_RFJ0": 1.74,
      "rh_RFJ3": 0.65,
      "rh_RFJ4": -0.33513600000000004,
      "rh_THJ1": 0.0,
      "rh_THJ2": 0.35,
      "rh_THJ4": 0.5,
      "rh_THJ5": 0.4
    },
    "gap": {
      "rh_FFJ0": 0.0054811903722067346,
      "rh_FFJ3": 0.001235558062360198,
      "rh_FFJ4": 0.0017068312155745224,
      "rh_MFJ0": 0.0034964583614724987,
      "rh_MFJ3": 0.0013250372794192389,
      "rh_MFJ4": 0.0036616148041375856,
      "rh_RFJ0": 0.000425889881503716,
      "rh_RFJ3": 5.710617215815006e-05,
      "rh_RFJ4": 0.0012041384993167759,
      "rh_THJ1": 0.007689686444523178,
      "rh_THJ2": 0.005805406137135871,
      "rh_THJ4": 0.0028595763894256887,
      "rh_THJ5": 0.0028053079059576214
    },
    "max_gap_rad": 0.007689686444523178
  }
}